MANIFEST.in
README
setup.py
Turk.egg-info/PKG-INFO
Turk.egg-info/SOURCES.txt
Turk.egg-info/dependency_links.txt
Turk.egg-info/entry_points.txt
Turk.egg-info/requires.txt
Turk.egg-info/top_level.txt
turk/__init__.py
turk/turk.yml
turk/turkctl.py
turk/dbus/org.turkinnovations.turk.conf
turk/drivers/interactable.py
turk/drivers/pixel_clock.py
turk/drivers/rgb_lamp.py
turk/drivers/twitter_fetcher.py
turk/runtime/__init__.py
turk/runtime/bridge.py
turk/runtime/spawner.py
turk/utils/__init__.py
turk/utils/signal.py
turk/xbeed/__init__.py
turk/xbeed/testing.py
turk/xbeed/xbeed.py